amplified.py
amplified-0.0.0.dist-info/WHEEL
amplified-0.0.0.dist-info/METADATA
amplified-0.0.0.dist-info/RECORD
